{
  "name": "Zombie Carnival of Doom",
  "meta": {
    "author": "Kamie Kehrwald",
    "welcome": ""
  },
  "locations": [{
    "loc1": {
      "alias": "Front Gate",
      "description": "The entrance is made up to look like the wide gaping mouth of a sinister looking clown, but you'll be darned if you miss the one bit of excitement to come to your town in months",
      "hint": "Go Entrance",
      "actions": null,
      "exits": {
        "entrance": "loc2"
      },
      "objects": null
    }
  }, {
    "loc2": {
      "alias": "Entrance",
      "description": "Through the entrance you come to an open area to your left is a fortune teller and to your right is the freak show. Too bad for you, right now you can only go back out the entrance ",
      "hint": "Go Front Gate",
      "actions": null,
      "exits": {
        "Front Gate": "loc1"
      },
      "objects": {
        "bottle": {
          "actions": null
        }
      },
      "enemies": null
    }
  }]
}